algomock/__init__.py
algomock/generator.py
algomock/utils.py
tests/__init__.py
tests/test_generator.py
algomock-0.2.0.dist-info/LICENSE
algomock-0.2.0.dist-info/METADATA
algomock-0.2.0.dist-info/WHEEL
algomock-0.2.0.dist-info/top_level.txt
algomock-0.2.0.dist-info/RECORD
