Metadata-Version: 2.1
Name: algomock
Version: 0.2.0
Summary: A flexible input generator for algorithm testing
Home-page: https://github.com/getCurrentThread/algomock
Author: getCurrentThread
Author-email: wak8835@gmail.com
Classifier: Programming Language :: Python :: 3
Classifier: License :: OSI Approved :: MIT License
Classifier: Operating System :: OS Independent
Requires-Python: >=3.6
License-File: LICENSE
